deezer/__init__.py
deezer/api.py
deezer/errors.py
deezer/gw.py
deezer/utils.py
deezer_py-1.3.7.dist-info/LICENSE.txt
deezer_py-1.3.7.dist-info/METADATA
deezer_py-1.3.7.dist-info/WHEEL
deezer_py-1.3.7.dist-info/top_level.txt
deezer_py-1.3.7.dist-info/RECORD
