Metadata-Version: 2.1
Name: deezer-py
Version: 1.3.7
Summary: A wrapper for all Deezer's APIs
Home-page: UNKNOWN
Author: RemixDev
Author-email: RemixDev64@gmail.com
License: GPL3
Platform: UNKNOWN
Classifier: License :: OSI Approved :: GNU General Public License v3 (GPLv3)
Classifier: Programming Language :: Python :: 3 :: Only
Classifier: Programming Language :: Python :: 3.6
Classifier: Programming Language :: Python :: 3.7
Classifier: Programming Language :: Python :: 3.8
Classifier: Operating System :: OS Independent
Requires-Python: >=3.6
License-File: LICENSE.txt
